SmolBit/Converter.py
SmolBit/SyntaxChecker.py
SmolBit/__init__.py
SmolBit/__main__.py
SmolBit/smolbitCore.py
smolbit-2.0.4.post3.dist-info/METADATA
smolbit-2.0.4.post3.dist-info/WHEEL
smolbit-2.0.4.post3.dist-info/top_level.txt
smolbit-2.0.4.post3.dist-info/RECORD
