Metadata-Version: 2.4
Name: SmolBit
Version: 2.0.4.post3
Summary: A tiny little programming language made with python
Author-email: Smol <kingalexander471@gmail.com>
License-Expression: MIT
Requires-Python: >=3.12
Requires-Dist: colorama>=0.4.6
